hello/__init__.py
hello/hello.py
hellotimostar/__init__.py
hellotimostar/hello.py
hellotimostar-1.0.1.dist-info/DESCRIPTION.rst
hellotimostar-1.0.1.dist-info/METADATA
hellotimostar-1.0.1.dist-info/RECORD
hellotimostar-1.0.1.dist-info/WHEEL
hellotimostar-1.0.1.dist-info/entry_points.txt
hellotimostar-1.0.1.dist-info/metadata.json
hellotimostar-1.0.1.dist-info/top_level.txt
