Metadata-Version: 2.0
Name: hellotimostar
Version: 1.0.1
Summary: UNKNOWN
Home-page: https://yandex.ru
Author: Timofey Starodubtsev
Author-email: timostar98@gmail.com
License: UNKNOWN
Platform: UNKNOWN
Requires-Dist: Flask
